pyculus/__init__.py
pyculus-0.0.12.dist-info/METADATA
pyculus-0.0.12.dist-info/WHEEL
pyculus-0.0.12.dist-info/licenses/LICENSE
pyculus-0.0.12.dist-info/RECORD
