Metadata-Version: 2.4
Name: pyculus
Version: 0.0.12
Summary: a collection of calculus-related functions
Author-email: Maayan Keidar <pythonfunctionslibrery@gmail.com>
License-File: LICENSE
Classifier: License :: OSI Approved :: GNU General Public License v3 (GPLv3)
Classifier: Operating System :: OS Independent
Classifier: Programming Language :: Python :: 3
Requires-Python: >=3.7
Requires-Dist: matplotlib
Requires-Dist: numpy
Requires-Dist: sympy
